chasta/__init__.py
chasta/chasta.py
chasta-0.1.6.dist-info/METADATA
chasta-0.1.6.dist-info/WHEEL
chasta-0.1.6.dist-info/entry_points.txt
chasta-0.1.6.dist-info/RECORD
