Metadata-Version: 2.1
Name: chasta
Version: 0.1.6
Summary: CHArt and run STAtitics on CSV data
Author: Jerome Provensal
Author-email: jeromegit@provensal.com
Requires-Python: >=3.9,<4.0
Classifier: Programming Language :: Python :: 3
Classifier: Programming Language :: Python :: 3.9
Classifier: Programming Language :: Python :: 3.10
Classifier: Programming Language :: Python :: 3.11
Requires-Dist: pandas (>=2.0.3,<3.0.0)
Requires-Dist: plotly (>=5.15.0,<6.0.0)
